lohi_splitter/__init__.py
lohi_splitter/lo_splitter.py
lohi_splitter/min_vertex_k_cut.py
lohi_splitter/utils.py
lohi_splitter-1.1.dist-info/METADATA
lohi_splitter-1.1.dist-info/WHEEL
lohi_splitter-1.1.dist-info/licenses/LICENSE
lohi_splitter-1.1.dist-info/RECORD
