Metadata-Version: 2.1
Name: lohi_splitter
Version: 1.1
Summary: Train-test splitter for Lead Optimization and Hit Identification tasks.
Project-URL: Homepage, https://github.com/SteshinSS/lohi_splitter
Project-URL: Bug Tracker, https://github.com/SteshinSS/lohi_splitter/issues
Author-email: Simon Steshin <simon.steshin@gmail.com>
License-File: LICENSE
Classifier: License :: OSI Approved :: MIT License
Classifier: Operating System :: OS Independent
Classifier: Programming Language :: Python :: 3
Requires-Python: >=3.7
Requires-Dist: mip==1.15.0
Requires-Dist: networkx
Requires-Dist: numpy
Requires-Dist: rdkit-pypi>=2022.09.1
Requires-Dist: tqdm
